amzlforecasting/__init__.py
amzlforecasting/forecasting.py
amzlforecasting-0.1.dist-info/METADATA
amzlforecasting-0.1.dist-info/WHEEL
amzlforecasting-0.1.dist-info/top_level.txt
amzlforecasting-0.1.dist-info/RECORD
