Metadata-Version: 2.1
Name: amzlforecasting
Version: 0.1
Summary: common functions and datasets for AMZL forecasting
Home-page: https://github.com/arahas/amzlforecasting
Author: Jinwoo Je
Classifier: Programming Language :: Python :: 3
Classifier: License :: OSI Approved :: MIT License
Classifier: Operating System :: OS Independent
Requires-Python: >=3.6
Requires-Dist: pandas
